{"name":"深拷贝","postlist":[{"title":"antd 中 Table 的 dataSource 不更新？？","slug":"antd中Table的dataSource不更新？？","date":"2022-01-14","updated":"2022-01-14","path":"api/posts/34168.json","excerpt":"<p> 答应我，别再修改对象属性的时候不深拷贝原对象了！</p><p></p>","cover":"/gallery/bg-001.jpeg","content":null,"min2read":1,"word4post":511,"url":"/posts/34168/","categories":[{"name":"深拷贝","path":"api/categories/深拷贝.json","url":"/categories/深拷贝/"}],"tags":[{"name":"antd, 深拷贝","path":"api/tags/antd, 深拷贝.json","url":"/tags/antd-深拷贝/"}]}]}